{
"meta":{"test_sets":[],"test_metrics":[],"learn_metrics":[{"best_value":"Min","name":"RMSE"}],"launch_mode":"Train","parameters":"","iteration_count":700,"learn_sets":["learn"],"name":"experiment"},
"iterations":[
{"learn":[0.3835803083],"iteration":0,"passed_time":0.05551817974,"remaining_time":38.80720764},
{"learn":[0.3710942565],"iteration":1,"passed_time":0.08684366738,"remaining_time":30.30843992},
{"learn":[0.3586243618],"iteration":2,"passed_time":0.09743526742,"remaining_time":22.63746046},
{"learn":[0.3470765125],"iteration":3,"passed_time":0.1117533246,"remaining_time":19.44507848},
{"learn":[0.3371295444],"iteration":4,"passed_time":0.1205609702,"remaining_time":16.75797486},
{"learn":[0.3262325137],"iteration":5,"passed_time":0.1518986132,"remaining_time":17.56960626},
{"learn":[0.3164906835],"iteration":6,"passed_time":0.1673971121,"remaining_time":16.57231409},
{"learn":[0.3064204357],"iteration":7,"passed_time":0.1745725265,"remaining_time":15.10052354},
{"learn":[0.297848659],"iteration":8,"passed_time":0.1814228206,"remaining_time":13.92924101},
{"learn":[0.2898590979],"iteration":9,"passed_time":0.1879132268,"remaining_time":12.96601265},
{"learn":[0.2814123558],"iteration":10,"passed_time":0.2005429072,"remaining_time":12.56127846},
{"learn":[0.2729857053],"iteration":11,"passed_time":0.2067288034,"remaining_time":11.8524514},
{"learn":[0.2657516886],"iteration":12,"passed_time":0.2143076609,"remaining_time":11.32533562},
{"learn":[0.2581505959],"iteration":13,"passed_time":0.2237254531,"remaining_time":10.9625472},
{"learn":[0.2509471863],"iteration":14,"passed_time":0.2307022817,"remaining_time":10.5354042},
{"learn":[0.2449977705],"iteration":15,"passed_time":0.2365306792,"remaining_time":10.11168654},
{"learn":[0.2391420113],"iteration":16,"passed_time":0.2425766605,"remaining_time":9.745874065},
{"learn":[0.233118735],"iteration":17,"passed_time":0.2493985036,"remaining_time":9.449432192},
{"learn":[0.2273598438],"iteration":18,"passed_time":0.2551445631,"remaining_time":9.144918289},
{"learn":[0.2219767023],"iteration":19,"passed_time":0.2610402166,"remaining_time":8.875367366},
{"learn":[0.2167981461],"iteration":20,"passed_time":0.2681980974,"remaining_time":8.671738483},
{"learn":[0.2121581731],"iteration":21,"passed_time":0.2739762177,"remaining_time":8.443448892},
{"learn":[0.2078356397],"iteration":22,"passed_time":0.2789869244,"remaining_time":8.211919471},
{"learn":[0.2036617212],"iteration":23,"passed_time":0.284308742,"remaining_time":8.008029566},
{"learn":[0.1991451691],"iteration":24,"passed_time":0.2930187952,"remaining_time":7.911507471},
{"learn":[0.1946579883],"iteration":25,"passed_time":0.2988980341,"remaining_time":7.748356729},
{"learn":[0.1905953596],"iteration":26,"passed_time":0.3046294682,"remaining_time":7.593171558},
{"learn":[0.1867792341],"iteration":27,"passed_time":0.3101388462,"remaining_time":7.44333231},
{"learn":[0.1834001166],"iteration":28,"passed_time":0.3159434405,"remaining_time":7.310277536},
{"learn":[0.1798057397],"iteration":29,"passed_time":0.3222670995,"remaining_time":7.197298555},
{"learn":[0.1768520702],"iteration":30,"passed_time":0.3282681549,"remaining_time":7.084238569},
{"learn":[0.1736063426],"iteration":31,"passed_time":0.3336299159,"remaining_time":6.964524494},
{"learn":[0.1706558103],"iteration":32,"passed_time":0.3389422981,"remaining_time":6.850742813},
{"learn":[0.1677712247],"iteration":33,"passed_time":0.3454172295,"remaining_time":6.766113965},
{"learn":[0.164843312],"iteration":34,"passed_time":0.3509028302,"remaining_time":6.667153774},
{"learn":[0.1621220804],"iteration":35,"passed_time":0.3566257923,"remaining_time":6.577764614},
{"learn":[0.1598790954],"iteration":36,"passed_time":0.3630163123,"remaining_time":6.504859867},
{"learn":[0.1573362018],"iteration":37,"passed_time":0.3701111645,"remaining_time":6.447726077},
{"learn":[0.1550459096],"iteration":38,"passed_time":0.376344318,"remaining_time":6.378553697},
{"learn":[0.1530040731],"iteration":39,"passed_time":0.3848571295,"remaining_time":6.350142637},
{"learn":[0.1510393479],"iteration":40,"passed_time":0.3957564355,"remaining_time":6.361060756},
{"learn":[0.1491562244],"iteration":41,"passed_time":0.4089769139,"remaining_time":6.407304984},
{"learn":[0.1474087879],"iteration":42,"passed_time":0.4192558196,"remaining_time":6.405838917},
{"learn":[0.1456303057],"iteration":43,"passed_time":0.4280388438,"remaining_time":6.381670034},
{"learn":[0.1437712843],"iteration":44,"passed_time":0.4407064834,"remaining_time":6.414727703},
{"learn":[0.1421920997],"iteration":45,"passed_time":0.4577073524,"remaining_time":6.507404531},
{"learn":[0.1406688235],"iteration":46,"passed_time":0.4660370935,"remaining_time":6.474940895},
{"learn":[0.1392316852],"iteration":47,"passed_time":0.4731798866,"remaining_time":6.427360126},
{"learn":[0.1377260266],"iteration":48,"passed_time":0.479835784,"remaining_time":6.37496113},
{"learn":[0.1358807997],"iteration":49,"passed_time":0.4856229498,"remaining_time":6.313098347},
{"learn":[0.1345260459],"iteration":50,"passed_time":0.4924403409,"remaining_time":6.266544731},
{"learn":[0.1333838681],"iteration":51,"passed_time":0.5006381409,"remaining_time":6.238721448},
{"learn":[0.1322453701],"iteration":52,"passed_time":0.508610752,"remaining_time":6.208889746},
{"learn":[0.1311775964],"iteration":53,"passed_time":0.5152683932,"remaining_time":6.164136704},
{"learn":[0.1300128556],"iteration":54,"passed_time":0.5226046998,"remaining_time":6.128727843},
{"learn":[0.1289447609],"iteration":55,"passed_time":0.5288731912,"remaining_time":6.082041699},
{"learn":[0.1279762906],"iteration":56,"passed_time":0.5348015557,"remaining_time":6.032936847},
{"learn":[0.1269733947],"iteration":57,"passed_time":0.5407808522,"remaining_time":5.985884606},
{"learn":[0.1258573609],"iteration":58,"passed_time":0.547125028,"remaining_time":5.944188864},
{"learn":[0.1247810124],"iteration":59,"passed_time":0.5562397792,"remaining_time":5.933224311},
{"learn":[0.1237338596],"iteration":60,"passed_time":0.5658225904,"remaining_time":5.927223529},
{"learn":[0.1230398544],"iteration":61,"passed_time":0.5716865765,"remaining_time":5.882839287},
{"learn":[0.1222801504],"iteration":62,"passed_time":0.5778608498,"remaining_time":5.842815259},
{"learn":[0.1216147659],"iteration":63,"passed_time":0.5834334945,"remaining_time":5.797870351},
{"learn":[0.1207631163],"iteration":64,"passed_time":0.5908605415,"remaining_time":5.772252983},
{"learn":[0.1198818448],"iteration":65,"passed_time":0.5967678988,"remaining_time":5.732588603},
{"learn":[0.1192167518],"iteration":66,"passed_time":0.6025041547,"remaining_time":5.692315372},
{"learn":[0.1185996736],"iteration":67,"passed_time":0.6086490145,"remaining_time":5.656855547},
{"learn":[0.1178408445],"iteration":68,"passed_time":0.6163625846,"remaining_time":5.636591173},
{"learn":[0.1171996293],"iteration":69,"passed_time":0.6219056483,"remaining_time":5.597150835},
{"learn":[0.1165334886],"iteration":70,"passed_time":0.6280029034,"remaining_time":5.563575017},
{"learn":[0.1157812373],"iteration":71,"passed_time":0.6341994733,"remaining_time":5.531628739},
{"learn":[0.1151557501],"iteration":72,"passed_time":0.640637083,"remaining_time":5.502458233},
{"learn":[0.1144557783],"iteration":73,"passed_time":0.6468299091,"remaining_time":5.471831393},
{"learn":[0.113851034],"iteration":74,"passed_time":0.6521030702,"remaining_time":5.434192251},
{"learn":[0.1130903692],"iteration":75,"passed_time":0.6576424138,"remaining_time":5.399590345},
{"learn":[0.1125193459],"iteration":76,"passed_time":0.6644096349,"remaining_time":5.375677955},
{"learn":[0.1120630063],"iteration":77,"passed_time":0.6724650031,"remaining_time":5.362477332},
{"learn":[0.1114237901],"iteration":78,"passed_time":0.6786628802,"remaining_time":5.334805679},
{"learn":[0.1108059256],"iteration":79,"passed_time":0.6938653309,"remaining_time":5.377456314},
{"learn":[0.1101995398],"iteration":80,"passed_time":0.7002468778,"remaining_time":5.35126935},
{"learn":[0.1096291603],"iteration":81,"passed_time":0.7065815221,"remaining_time":5.325211959},
{"learn":[0.1092310631],"iteration":82,"passed_time":0.7121134696,"remaining_time":5.29366278},
{"learn":[0.1087997416],"iteration":83,"passed_time":0.7179647382,"remaining_time":5.265074746},
{"learn":[0.1083965584],"iteration":84,"passed_time":0.7237543796,"remaining_time":5.236575806},
{"learn":[0.1078113568],"iteration":85,"passed_time":0.7305795453,"remaining_time":5.215998149},
{"learn":[0.1072885961],"iteration":86,"passed_time":0.7381748901,"remaining_time":5.201163306},
{"learn":[0.1069298306],"iteration":87,"passed_time":0.7448390234,"remaining_time":5.180016844},
{"learn":[0.1065451837],"iteration":88,"passed_time":0.7507698761,"remaining_time":5.154161734},
{"learn":[0.1061878304],"iteration":89,"passed_time":0.7556355143,"remaining_time":5.121529597},
{"learn":[0.1057133005],"iteration":90,"passed_time":0.7611722432,"remaining_time":5.093998859},
{"learn":[0.1053539054],"iteration":91,"passed_time":0.7682001999,"remaining_time":5.076801321},
{"learn":[0.1049190664],"iteration":92,"passed_time":0.7743186811,"remaining_time":5.053886446},
{"learn":[0.1045656725],"iteration":93,"passed_time":0.7802963529,"remaining_time":5.030421169},
{"learn":[0.1041640068],"iteration":94,"passed_time":0.7900721286,"remaining_time":5.031511977},
{"learn":[0.1036673021],"iteration":95,"passed_time":0.7981412692,"remaining_time":5.021638818},
{"learn":[0.1031342587],"iteration":96,"passed_time":0.8062539149,"remaining_time":5.012073306},
{"learn":[0.1027708356],"iteration":97,"passed_time":0.8139206105,"remaining_time":4.999798036},
{"learn":[0.1025439793],"iteration":98,"passed_time":0.8232691866,"remaining_time":4.997826072},
{"learn":[0.1021362747],"iteration":99,"passed_time":0.830425564,"remaining_time":4.982553384},
{"learn":[0.1018688994],"iteration":100,"passed_time":0.8374714917,"remaining_time":4.966786371},
{"learn":[0.1014128458],"iteration":101,"passed_time":0.84404157,"remaining_time":4.948400577},
{"learn":[0.1009679733],"iteration":102,"passed_time":0.8521940642,"remaining_time":4.939416081},
{"learn":[0.100498311],"iteration":103,"passed_time":0.8596182719,"remaining_time":4.926273943},
{"learn":[0.1001619736],"iteration":104,"passed_time":0.8678373305,"remaining_time":4.917744873},
{"learn":[0.09975453527],"iteration":105,"passed_time":0.8749734001,"remaining_time":4.903152827},
{"learn":[0.09936783521],"iteration":106,"passed_time":0.8815555749,"remaining_time":4.885630429},
{"learn":[0.09908062027],"iteration":107,"passed_time":0.8900298421,"remaining_time":4.878682098},
{"learn":[0.09886170356],"iteration":108,"passed_time":0.8979360573,"remaining_time":4.868625779},
{"learn":[0.09857475309],"iteration":109,"passed_time":0.9039822237,"remaining_time":4.848631927},
{"learn":[0.09822735838],"iteration":110,"passed_time":0.9100133878,"remaining_time":4.828809779},
{"learn":[0.09795857357],"iteration":111,"passed_time":0.9188156253,"remaining_time":4.823782033},
{"learn":[0.09774935311],"iteration":112,"passed_time":0.9350799362,"remaining_time":4.857450642},
{"learn":[0.09742977583],"iteration":113,"passed_time":0.9481805761,"remaining_time":4.873980856},
{"learn":[0.0971207375],"iteration":114,"passed_time":0.9545502818,"remaining_time":4.855755781},
{"learn":[0.09688321734],"iteration":115,"passed_time":0.9613806151,"remaining_time":4.840054131},
{"learn":[0.09651077732],"iteration":116,"passed_time":0.9682355794,"remaining_time":4.824626862},
{"learn":[0.0961669984],"iteration":117,"passed_time":0.9760180337,"remaining_time":4.813919455},
{"learn":[0.09596021769],"iteration":118,"passed_time":0.9831948688,"remaining_time":4.800304359},
{"learn":[0.09572623312],"iteration":119,"passed_time":0.9898992736,"remaining_time":4.784513156},
{"learn":[0.09552494858],"iteration":120,"passed_time":0.9957618147,"remaining_time":4.764843725},
{"learn":[0.09521807925],"iteration":121,"passed_time":1.003439708,"remaining_time":4.754001238},
{"learn":[0.09481118542],"iteration":122,"passed_time":1.010953253,"remaining_time":4.742439245},
{"learn":[0.09457265521],"iteration":123,"passed_time":1.017414304,"remaining_time":4.726053543},
{"learn":[0.09423198048],"iteration":124,"passed_time":1.023935702,"remaining_time":4.71010423},
{"learn":[0.09394680931],"iteration":125,"passed_time":1.029951303,"remaining_time":4.692000382},
{"learn":[0.09367759935],"iteration":126,"passed_time":1.036495876,"remaining_time":4.676473519},
{"learn":[0.09344681194],"iteration":127,"passed_time":1.046349414,"remaining_time":4.675873945},
{"learn":[0.09316402211],"iteration":128,"passed_time":1.055105021,"remaining_time":4.670271062},
{"learn":[0.09286564825],"iteration":129,"passed_time":1.060570723,"remaining_time":4.650194707},
{"learn":[0.09252207509],"iteration":130,"passed_time":1.066471686,"remaining_time":4.632231982},
{"learn":[0.09221567192],"iteration":131,"passed_time":1.074881924,"remaining_time":4.625249489},
{"learn":[0.09201512259],"iteration":132,"passed_time":1.082160675,"remaining_time":4.613421827},
{"learn":[0.09180243376],"iteration":133,"passed_time":1.091733055,"remaining_time":4.611350067},
{"learn":[0.09162329056],"iteration":134,"passed_time":1.105499326,"remaining_time":4.626719403},
{"learn":[0.09126625725],"iteration":135,"passed_time":1.116845257,"remaining_time":4.631622977},
{"learn":[0.09101622582],"iteration":136,"passed_time":1.12636804,"remaining_time":4.628797128},
{"learn":[0.09071347305],"iteration":137,"passed_time":1.136006648,"remaining_time":4.626345913},
{"learn":[0.09049688618],"iteration":138,"passed_time":1.14510932,"remaining_time":4.621628264},
{"learn":[0.09027870477],"iteration":139,"passed_time":1.153221203,"remaining_time":4.612884814},
{"learn":[0.09000056197],"iteration":140,"passed_time":1.159912218,"remaining_time":4.598517234},
{"learn":[0.08978689374],"iteration":141,"passed_time":1.169415558,"remaining_time":4.595309024},
{"learn":[0.08955585416],"iteration":142,"passed_time":1.175735871,"remaining_time":4.579614545},
{"learn":[0.08924452487],"iteration":143,"passed_time":1.181165755,"remaining_time":4.560612221},
{"learn":[0.08895377798],"iteration":144,"passed_time":1.187094902,"remaining_time":4.543708073},
{"learn":[0.08873074335],"iteration":145,"passed_time":1.192703756,"remaining_time":4.525738908},
{"learn":[0.08854616169],"iteration":146,"passed_time":1.198891167,"remaining_time":4.510114389},
{"learn":[0.08824384402],"iteration":147,"passed_time":1.20423802,"remaining_time":4.491482344},
{"learn":[0.08797755396],"iteration":148,"passed_time":1.209964293,"remaining_time":4.474431714},
{"learn":[0.08771554394],"iteration":149,"passed_time":1.215666012,"remaining_time":4.457442044},
{"learn":[0.08740226069],"iteration":150,"passed_time":1.221232914,"remaining_time":4.440111719},
{"learn":[0.08714017681],"iteration":151,"passed_time":1.22704226,"remaining_time":4.423810255},
{"learn":[0.08687779989],"iteration":152,"passed_time":1.233789097,"remaining_time":4.41099762},
{"learn":[0.08665132011],"iteration":153,"passed_time":1.239706407,"remaining_time":4.395322715},
{"learn":[0.08640705805],"iteration":154,"passed_time":1.245165356,"remaining_time":4.378162057},
{"learn":[0.08624824665],"iteration":155,"passed_time":1.25018535,"remaining_time":4.359620709},
{"learn":[0.08606110071],"iteration":156,"passed_time":1.255488758,"remaining_time":4.342231818},
{"learn":[0.08584592199],"iteration":157,"passed_time":1.260961896,"remaining_time":4.325578151},
{"learn":[0.08568047449],"iteration":158,"passed_time":1.26619406,"remaining_time":4.308245197},
{"learn":[0.08544423886],"iteration":159,"passed_time":1.27163145,"remaining_time":4.291756142},
{"learn":[0.08517373291],"iteration":160,"passed_time":1.277062587,"remaining_time":4.275383444},
{"learn":[0.08499685658],"iteration":161,"passed_time":1.282429073,"remaining_time":4.258931118},
{"learn":[0.08477919184],"iteration":162,"passed_time":1.287777749,"remaining_time":4.242556142},
{"learn":[0.08456559976],"iteration":163,"passed_time":1.292814562,"remaining_time":4.225296373},
{"learn":[0.08435472054],"iteration":164,"passed_time":1.298039317,"remaining_time":4.208794149},
{"learn":[0.08416875689],"iteration":165,"passed_time":1.303232636,"remaining_time":4.192326671},
{"learn":[0.08397464269],"iteration":166,"passed_time":1.309728521,"remaining_time":4.180151506},
{"learn":[0.08374523339],"iteration":167,"passed_time":1.315517743,"remaining_time":4.165806186},
{"learn":[0.08358566097],"iteration":168,"passed_time":1.32193161,"remaining_time":4.153524763},
{"learn":[0.08328486145],"iteration":169,"passed_time":1.327314851,"remaining_time":4.138099241},
{"learn":[0.08297723076],"iteration":170,"passed_time":1.332895457,"remaining_time":4.123401735},
{"learn":[0.0827975014],"iteration":171,"passed_time":1.338010231,"remaining_time":4.107380243},
{"learn":[0.0826113847],"iteration":172,"passed_time":1.34345119,"remaining_time":4.09247848},
{"learn":[0.08239168195],"iteration":173,"passed_time":1.349227761,"remaining_time":4.078700012},
{"learn":[0.08219780073],"iteration":174,"passed_time":1.354879171,"remaining_time":4.064637514},
{"learn":[0.08206580437],"iteration":175,"passed_time":1.360008198,"remaining_time":4.049115317},
{"learn":[0.08176951235],"iteration":176,"passed_time":1.365657683,"remaining_time":4.035248407},
{"learn":[0.08160256518],"iteration":177,"passed_time":1.371473511,"remaining_time":4.021961643},
{"learn":[0.08144779794],"iteration":178,"passed_time":1.37882948,"remaining_time":4.013241113},
{"learn":[0.08118070051],"iteration":179,"passed_time":1.385623048,"remaining_time":4.002911027},
{"learn":[0.08094673757],"iteration":180,"passed_time":1.392921863,"remaining_time":3.994068769},
{"learn":[0.08075888671],"iteration":181,"passed_time":1.399576248,"remaining_time":3.983409322},
{"learn":[0.08061692222],"iteration":182,"passed_time":1.405668711,"remaining_time":3.971206138},
{"learn":[0.08029999535],"iteration":183,"passed_time":1.420262523,"remaining_time":3.98291012},
{"learn":[0.08007355719],"iteration":184,"passed_time":1.425903527,"remaining_time":3.969407117},
{"learn":[0.07988653927],"iteration":185,"passed_time":1.431757642,"remaining_time":3.95657757},
{"learn":[0.07970527081],"iteration":186,"passed_time":1.438553205,"remaining_time":3.946405317},
{"learn":[0.07948784061],"iteration":187,"passed_time":1.447281196,"remaining_time":3.941531767},
{"learn":[0.07932038081],"iteration":188,"passed_time":1.454189497,"remaining_time":3.931697528},
{"learn":[0.07915386159],"iteration":189,"passed_time":1.460837107,"remaining_time":3.92119434},
{"learn":[0.07895883043],"iteration":190,"passed_time":1.46798566,"remaining_time":3.912066498},
{"learn":[0.07875903426],"iteration":191,"passed_time":1.473653948,"remaining_time":3.899042739},
{"learn":[0.0786001265],"iteration":192,"passed_time":1.478985046,"remaining_time":3.885209422},
{"learn":[0.07836356385],"iteration":193,"passed_time":1.484747328,"remaining_time":3.872588391},
{"learn":[0.07812060552],"iteration":194,"passed_time":1.48987925,"remaining_time":3.858405237},
{"learn":[0.07785863799],"iteration":195,"passed_time":1.495099565,"remaining_time":3.844541739},
{"learn":[0.07772576147],"iteration":196,"passed_time":1.502851822,"remaining_time":3.837230794},
{"learn":[0.07752446196],"iteration":197,"passed_time":1.508273085,"remaining_time":3.824005499},
{"learn":[0.07735121204],"iteration":198,"passed_time":1.51431002,"remaining_time":3.812408644},
{"learn":[0.07719620765],"iteration":199,"passed_time":1.519823046,"remaining_time":3.799557616},
{"learn":[0.07702154366],"iteration":200,"passed_time":1.525869359,"remaining_time":3.788103532},
{"learn":[0.07681408683],"iteration":201,"passed_time":1.53184608,"remaining_time":3.776531424},
{"learn":[0.07658566908],"iteration":202,"passed_time":1.537503049,"remaining_time":3.764231604},
{"learn":[0.07637414623],"iteration":203,"passed_time":1.54277017,"remaining_time":3.75104904},
{"learn":[0.07612617131],"iteration":204,"passed_time":1.548079799,"remaining_time":3.738046345},
{"learn":[0.0759841692],"iteration":205,"passed_time":1.553877058,"remaining_time":3.726287701},
{"learn":[0.07578632912],"iteration":206,"passed_time":1.55943826,"remaining_time":3.714024455},
{"learn":[0.07554480692],"iteration":207,"passed_time":1.56504556,"remaining_time":3.701934691},
{"learn":[0.07526999635],"iteration":208,"passed_time":1.571733751,"remaining_time":3.692446275},
{"learn":[0.07507997753],"iteration":209,"passed_time":1.577317501,"remaining_time":3.680407503},
{"learn":[0.07491110077],"iteration":210,"passed_time":1.582833346,"remaining_time":3.66827254},
{"learn":[0.07472199256],"iteration":211,"passed_time":1.588604847,"remaining_time":3.656788517},
{"learn":[0.07457245874],"iteration":212,"passed_time":1.594181142,"remaining_time":3.644911813},
{"learn":[0.07431249378],"iteration":213,"passed_time":1.600038933,"remaining_time":3.633733277},
{"learn":[0.0741265844],"iteration":214,"passed_time":1.605407683,"remaining_time":3.621501052},
{"learn":[0.07398563429],"iteration":215,"passed_time":1.610626122,"remaining_time":3.60899557},
{"learn":[0.07377472888],"iteration":216,"passed_time":1.615894856,"remaining_time":3.596669195},
{"learn":[0.07365074852],"iteration":217,"passed_time":1.621799098,"remaining_time":3.585812684},
{"learn":[0.07340033957],"iteration":218,"passed_time":1.628204196,"remaining_time":3.576101454},
{"learn":[0.07326726642],"iteration":219,"passed_time":1.635547671,"remaining_time":3.568467645},
{"learn":[0.07308619035],"iteration":220,"passed_time":1.643815574,"remaining_time":3.562840091},
{"learn":[0.07294724923],"iteration":221,"passed_time":1.670137581,"remaining_time":3.596061999},
{"learn":[0.07277558084],"iteration":222,"passed_time":1.680072196,"remaining_time":3.593697028},
{"learn":[0.0726610007],"iteration":223,"passed_time":1.689229697,"remaining_time":3.589613106},
{"learn":[0.07248199631],"iteration":224,"passed_time":1.701395435,"remaining_time":3.591834807},
{"learn":[0.07226356183],"iteration":225,"passed_time":1.70975963,"remaining_time":3.585956037},
{"learn":[0.07208134223],"iteration":226,"passed_time":1.723467221,"remaining_time":3.591189407},
{"learn":[0.0718949376],"iteration":227,"passed_time":1.729916747,"remaining_time":3.581231159},
{"learn":[0.07170432617],"iteration":228,"passed_time":1.737465447,"remaining_time":3.573564303},
{"learn":[0.07146546059],"iteration":229,"passed_time":1.744004361,"remaining_time":3.563834998},
{"learn":[0.07128933425],"iteration":230,"passed_time":1.750307433,"remaining_time":3.553654486},
{"learn":[0.07101335368],"iteration":231,"passed_time":1.757054606,"remaining_time":3.544403258},
{"learn":[0.0708349493],"iteration":232,"passed_time":1.763947072,"remaining_time":3.535464731},
{"learn":[0.07067502466],"iteration":233,"passed_time":1.773053998,"remaining_time":3.530953687},
{"learn":[0.0704638221],"iteration":234,"passed_time":1.778722225,"remaining_time":3.519599295},
{"learn":[0.0702549231],"iteration":235,"passed_time":1.785055274,"remaining_time":3.5096002},
{"learn":[0.07002206084],"iteration":236,"passed_time":1.790737814,"remaining_time":3.498361214},
{"learn":[0.06974038904],"iteration":237,"passed_time":1.796481094,"remaining_time":3.487286829},
{"learn":[0.06962438882],"iteration":238,"passed_time":1.80296383,"remaining_time":3.47768337},
{"learn":[0.06946116225],"iteration":239,"passed_time":1.809129544,"remaining_time":3.467498293},
{"learn":[0.06928152734],"iteration":240,"passed_time":1.816856646,"remaining_time":3.460320334},
{"learn":[0.06909075181],"iteration":241,"passed_time":1.826415832,"remaining_time":3.456605169},
{"learn":[0.06897858507],"iteration":242,"passed_time":1.832974679,"remaining_time":3.447199293},
{"learn":[0.0688325676],"iteration":243,"passed_time":1.838398851,"remaining_time":3.435696213},
{"learn":[0.06860709719],"iteration":244,"passed_time":1.844008457,"remaining_time":3.424587135},
{"learn":[0.06835802925],"iteration":245,"passed_time":1.849632056,"remaining_time":3.413548591},
{"learn":[0.06822870042],"iteration":246,"passed_time":1.856069624,"remaining_time":3.404046718},
{"learn":[0.06808162864],"iteration":247,"passed_time":1.863100654,"remaining_time":3.395651192},
{"learn":[0.06793398324],"iteration":248,"passed_time":1.869306467,"remaining_time":3.385771953},
{"learn":[0.06776291637],"iteration":249,"passed_time":1.874918216,"remaining_time":3.37485279},
{"learn":[0.06757880213],"iteration":250,"passed_time":1.881528574,"remaining_time":3.36576227},
{"learn":[0.06741544991],"iteration":251,"passed_time":1.888086579,"remaining_time":3.356598362},
{"learn":[0.06720155273],"iteration":252,"passed_time":1.893772152,"remaining_time":3.345913645},
{"learn":[0.0670809324],"iteration":253,"passed_time":1.900211296,"remaining_time":3.336591488},
{"learn":[0.06688534567],"iteration":254,"passed_time":1.905875742,"remaining_time":3.32594002},
{"learn":[0.06672565727],"iteration":255,"passed_time":1.911961532,"remaining_time":3.316058283},
{"learn":[0.06656335425],"iteration":256,"passed_time":1.917693847,"remaining_time":3.305596787},
{"learn":[0.06643520823],"iteration":257,"passed_time":1.92390343,"remaining_time":3.295989597},
{"learn":[0.06633878712],"iteration":258,"passed_time":1.929882886,"remaining_time":3.286016806},
{"learn":[0.06623018349],"iteration":259,"passed_time":1.935478722,"remaining_time":3.27542553},
{"learn":[0.0660388899],"iteration":260,"passed_time":1.941138341,"remaining_time":3.264979815},
{"learn":[0.0658560783],"iteration":261,"passed_time":1.947425559,"remaining_time":3.255619828},
{"learn":[0.06575832488],"iteration":262,"passed_time":1.953767059,"remaining_time":3.246373402},
{"learn":[0.06567801723],"iteration":263,"passed_time":1.960033085,"remaining_time":3.237024338},
{"learn":[0.06559085372],"iteration":264,"passed_time":1.965953824,"remaining_time":3.227131748},
{"learn":[0.06540713975],"iteration":265,"passed_time":1.9723954,"remaining_time":3.21811881},
{"learn":[0.0651920421],"iteration":266,"passed_time":1.978123025,"remaining_time":3.207967303},
{"learn":[0.06502453726],"iteration":267,"passed_time":1.983951261,"remaining_time":3.198010989},
{"learn":[0.06490713006],"iteration":268,"passed_time":1.989529801,"remaining_time":3.187685294},
{"learn":[0.06472693932],"iteration":269,"passed_time":1.995559307,"remaining_time":3.178112971},
{"learn":[0.06458096308],"iteration":270,"passed_time":2.001056631,"remaining_time":3.167724335},
{"learn":[0.06442490841],"iteration":271,"passed_time":2.006835449,"remaining_time":3.157814604},
{"learn":[0.06431608761],"iteration":272,"passed_time":2.012672051,"remaining_time":3.148025516},
{"learn":[0.06424551113],"iteration":273,"passed_time":2.018227099,"remaining_time":3.137827534},
{"learn":[0.06410328669],"iteration":274,"passed_time":2.024346905,"remaining_time":3.128536126},
{"learn":[0.06390635516],"iteration":275,"passed_time":2.029811004,"remaining_time":3.118260384},
{"learn":[0.06377197607],"iteration":276,"passed_time":2.035732723,"remaining_time":3.108718201},
{"learn":[0.06361390253],"iteration":277,"passed_time":2.041261265,"remaining_time":3.09860523},
{"learn":[0.06347183733],"iteration":278,"passed_time":2.046738995,"remaining_time":3.088448448},
{"learn":[0.06331365798],"iteration":279,"passed_time":2.052493308,"remaining_time":3.078739962},
{"learn":[0.06304096274],"iteration":280,"passed_time":2.058064233,"remaining_time":3.068786169},
{"learn":[0.06275839569],"iteration":281,"passed_time":2.063831475,"remaining_time":3.059154456},
{"learn":[0.06256430007],"iteration":282,"passed_time":2.069048924,"remaining_time":3.048739933},
{"learn":[0.06237282306],"iteration":283,"passed_time":2.074285734,"remaining_time":3.038390371},
{"learn":[0.06226502366],"iteration":284,"passed_time":2.080821629,"remaining_time":3.029968337},
{"learn":[0.0620899134],"iteration":285,"passed_time":2.086130289,"remaining_time":3.019783005},
{"learn":[0.06195669621],"iteration":286,"passed_time":2.09122974,"remaining_time":3.009330602},
{"learn":[0.06180665067],"iteration":287,"passed_time":2.096478368,"remaining_time":2.999128776},
{"learn":[0.06172046022],"iteration":288,"passed_time":2.10173886,"remaining_time":2.988978102},
{"learn":[0.06157252601],"iteration":289,"passed_time":2.106783021,"remaining_time":2.978555305},
{"learn":[0.06140522766],"iteration":290,"passed_time":2.112851312,"remaining_time":2.969608889},
{"learn":[0.06127711497],"iteration":291,"passed_time":2.118431297,"remaining_time":2.959999895},
{"learn":[0.06111373159],"iteration":292,"passed_time":2.124127775,"remaining_time":2.950580219},
{"learn":[0.06097070125],"iteration":293,"passed_time":2.129792031,"remaining_time":2.941141376},
{"learn":[0.06077188532],"iteration":294,"passed_time":2.135620167,"remaining_time":2.93195311},
{"learn":[0.06065155508],"iteration":295,"passed_time":2.141009984,"remaining_time":2.922189302},
{"learn":[0.06049159791],"iteration":296,"passed_time":2.146747982,"remaining_time":2.912927397},
{"learn":[0.06043036102],"iteration":297,"passed_time":2.152331292,"remaining_time":2.903480468},
{"learn":[0.06035518492],"iteration":298,"passed_time":2.158433167,"remaining_time":2.894754849},
{"learn":[0.06022047649],"iteration":299,"passed_time":2.163901535,"remaining_time":2.885202047},
{"learn":[0.06013162118],"iteration":300,"passed_time":2.169863616,"remaining_time":2.876330839},
{"learn":[0.06000991074],"iteration":301,"passed_time":2.175489059,"remaining_time":2.867035249},
{"learn":[0.05995704546],"iteration":302,"passed_time":2.180982662,"remaining_time":2.857591145},
{"learn":[0.05985674824],"iteration":303,"passed_time":2.188164721,"remaining_time":2.850372466},
{"learn":[0.0597683922],"iteration":304,"passed_time":2.193732134,"remaining_time":2.841062928},
{"learn":[0.05960730586],"iteration":305,"passed_time":2.199613556,"remaining_time":2.832182161},
{"learn":[0.05945773515],"iteration":306,"passed_time":2.206189629,"remaining_time":2.824210177},
{"learn":[0.05928931351],"iteration":307,"passed_time":2.212317542,"remaining_time":2.815676872},
{"learn":[0.05912831841],"iteration":308,"passed_time":2.218298059,"remaining_time":2.806972625},
{"learn":[0.05901197204],"iteration":309,"passed_time":2.22449304,"remaining_time":2.79855576},
{"learn":[0.05888327424],"iteration":310,"passed_time":2.230157275,"remaining_time":2.789489325},
{"learn":[0.05877547268],"iteration":311,"passed_time":2.235459872,"remaining_time":2.779994969},
{"learn":[0.05867024175],"iteration":312,"passed_time":2.240638939,"remaining_time":2.770374662},
{"learn":[0.0585559837],"iteration":313,"passed_time":2.245800494,"remaining_time":2.760761116},
{"learn":[0.05836958846],"iteration":314,"passed_time":2.251480064,"remaining_time":2.751808967},
{"learn":[0.05827072974],"iteration":315,"passed_time":2.257120611,"remaining_time":2.74283011},
{"learn":[0.05815291671],"iteration":316,"passed_time":2.262600645,"remaining_time":2.733678382},
{"learn":[0.05803248037],"iteration":317,"passed_time":2.26782612,"remaining_time":2.724243956},
{"learn":[0.05790175504],"iteration":318,"passed_time":2.273861181,"remaining_time":2.715802852},
{"learn":[0.0578731939],"iteration":319,"passed_time":2.279168494,"remaining_time":2.706512587},
{"learn":[0.05776919221],"iteration":320,"passed_time":2.285219891,"remaining_time":2.698125666},
{"learn":[0.0576401075],"iteration":321,"passed_time":2.291073452,"remaining_time":2.689521009},
{"learn":[0.05750911756],"iteration":322,"passed_time":2.296954905,"remaining_time":2.680965942},
{"learn":[0.05736994112],"iteration":323,"passed_time":2.303021943,"remaining_time":2.672642749},
{"learn":[0.05731299063],"iteration":324,"passed_time":2.308473353,"remaining_time":2.663623099},
{"learn":[0.05720354349],"iteration":325,"passed_time":2.314797887,"remaining_time":2.655627024},
{"learn":[0.05709262875],"iteration":326,"passed_time":2.320488261,"remaining_time":2.646917802},
{"learn":[0.05696389056],"iteration":327,"passed_time":2.326470825,"remaining_time":2.638558374},
{"learn":[0.05685342989],"iteration":328,"passed_time":2.332301235,"remaining_time":2.630041818},
{"learn":[0.05674306315],"iteration":329,"passed_time":2.339799226,"remaining_time":2.623411253},
{"learn":[0.05658814477],"iteration":330,"passed_time":2.345791741,"remaining_time":2.615097137},
{"learn":[0.0564565366],"iteration":331,"passed_time":2.351699892,"remaining_time":2.606703495},
{"learn":[0.05624667067],"iteration":332,"passed_time":2.35726793,"remaining_time":2.597949941},
{"learn":[0.05615416175],"iteration":333,"passed_time":2.363060567,"remaining_time":2.589461579},
{"learn":[0.05602053253],"iteration":334,"passed_time":2.368861856,"remaining_time":2.580998738},
{"learn":[0.05593246666],"iteration":335,"passed_time":2.374162134,"remaining_time":2.572008978},
{"learn":[0.05579642661],"iteration":336,"passed_time":2.380234284,"remaining_time":2.563872537},
{"learn":[0.05569872408],"iteration":337,"passed_time":2.385471819,"remaining_time":2.554854433},
{"learn":[0.05557669919],"iteration":338,"passed_time":2.391279933,"remaining_time":2.546466241},
{"learn":[0.05554136408],"iteration":339,"passed_time":2.39704967,"remaining_time":2.538052592},
{"learn":[0.05547574636],"iteration":340,"passed_time":2.402846649,"remaining_time":2.529683129},
{"learn":[0.05533465983],"iteration":341,"passed_time":2.408863227,"remaining_time":2.521558583},
{"learn":[0.05525880653],"iteration":342,"passed_time":2.414157535,"remaining_time":2.512694577},
{"learn":[0.05510400095],"iteration":343,"passed_time":2.420477226,"remaining_time":2.504912478},
{"learn":[0.05497136803],"iteration":344,"passed_time":2.426986719,"remaining_time":2.49733416},
{"learn":[0.05480141404],"iteration":345,"passed_time":2.432333576,"remaining_time":2.488572503},
{"learn":[0.0547055963],"iteration":346,"passed_time":2.438126053,"remaining_time":2.480283852},
{"learn":[0.0545714479],"iteration":347,"passed_time":2.443416762,"remaining_time":2.471502012},
{"learn":[0.05452917434],"iteration":348,"passed_time":2.448646479,"remaining_time":2.462678837},
{"learn":[0.05440380916],"iteration":349,"passed_time":2.454897348,"remaining_time":2.454897348},
{"learn":[0.05434461349],"iteration":350,"passed_time":2.460728752,"remaining_time":2.446707506},
{"learn":[0.0541708799],"iteration":351,"passed_time":2.466277246,"remaining_time":2.438251368},
{"learn":[0.05404127899],"iteration":352,"passed_time":2.472512613,"remaining_time":2.430486903},
{"learn":[0.05390275464],"iteration":353,"passed_time":2.478119633,"remaining_time":2.42211693},
{"learn":[0.05376840162],"iteration":354,"passed_time":2.484847158,"remaining_time":2.414851463},
{"learn":[0.05364962098],"iteration":355,"passed_time":2.491338607,"remaining_time":2.407360901},
{"learn":[0.05352986107],"iteration":356,"passed_time":2.496887833,"remaining_time":2.398970663},
{"learn":[0.05344028951],"iteration":357,"passed_time":2.502383799,"remaining_time":2.390545417},
{"learn":[0.05330005421],"iteration":358,"passed_time":2.50806367,"remaining_time":2.382311174},
{"learn":[0.05319653484],"iteration":359,"passed_time":2.513852109,"remaining_time":2.374193659},
{"learn":[0.05312338144],"iteration":360,"passed_time":2.519760671,"remaining_time":2.366201849},
{"learn":[0.05301945446],"iteration":361,"passed_time":2.525095739,"remaining_time":2.357686077},
{"learn":[0.05288223479],"iteration":362,"passed_time":2.531212597,"remaining_time":2.349913623},
{"learn":[0.05275858396],"iteration":363,"passed_time":2.537339294,"remaining_time":2.342159348},
{"learn":[0.05268506717],"iteration":364,"passed_time":2.542817997,"remaining_time":2.333819258},
{"learn":[0.05260466454],"iteration":365,"passed_time":2.547789646,"remaining_time":2.325032082},
{"learn":[0.05250687221],"iteration":366,"passed_time":2.553165062,"remaining_time":2.316632059},
{"learn":[0.05240388134],"iteration":367,"passed_time":2.55885714,"remaining_time":2.308534159},
{"learn":[0.0522997358],"iteration":368,"passed_time":2.565525736,"remaining_time":2.301325253},
{"learn":[0.0521866157],"iteration":369,"passed_time":2.571145234,"remaining_time":2.293183587},
{"learn":[0.05208680731],"iteration":370,"passed_time":2.576607358,"remaining_time":2.284915959},
{"learn":[0.05199649377],"iteration":371,"passed_time":2.584970272,"remaining_time":2.2792211},
{"learn":[0.05188477313],"iteration":372,"passed_time":2.592863568,"remaining_time":2.273100232},
{"learn":[0.05179966609],"iteration":373,"passed_time":2.601171101,"remaining_time":2.26733096},
{"learn":[0.05175355136],"iteration":374,"passed_time":2.609239829,"remaining_time":2.261341185},
{"learn":[0.05166460526],"iteration":375,"passed_time":2.61748652,"remaining_time":2.255493703},
{"learn":[0.05151387702],"iteration":376,"passed_time":2.625948812,"remaining_time":2.249818213},
{"learn":[0.05141156197],"iteration":377,"passed_time":2.63452392,"remaining_time":2.24422408},
{"learn":[0.05124220333],"iteration":378,"passed_time":2.642874286,"remaining_time":2.238423867},
{"learn":[0.05115695443],"iteration":379,"passed_time":2.650726571,"remaining_time":2.232190797},
{"learn":[0.0510057578],"iteration":380,"passed_time":2.6619704,"remaining_time":2.228788865},
{"learn":[0.05089909149],"iteration":381,"passed_time":2.671398034,"remaining_time":2.223833965},
{"learn":[0.05077721416],"iteration":382,"passed_time":2.680345937,"remaining_time":2.218458647},
{"learn":[0.05068005039],"iteration":383,"passed_time":2.689564482,"remaining_time":2.213287438},
{"learn":[0.0505690705],"iteration":384,"passed_time":2.698509771,"remaining_time":2.207871631},
{"learn":[0.05052355065],"iteration":385,"passed_time":2.712178114,"remaining_time":2.206279606},
{"learn":[0.05041657347],"iteration":386,"passed_time":2.724907775,"remaining_time":2.203865978},
{"learn":[0.05028022721],"iteration":387,"passed_time":2.738429401,"remaining_time":2.202036013},
{"learn":[0.05021387361],"iteration":388,"passed_time":2.74767744,"remaining_time":2.196729264},
{"learn":[0.05013932522],"iteration":389,"passed_time":2.761102552,"remaining_time":2.194722542},
{"learn":[0.05002538971],"iteration":390,"passed_time":2.774039898,"remaining_time":2.19227194},
{"learn":[0.0499456833],"iteration":391,"passed_time":2.782580021,"remaining_time":2.186312874},
{"learn":[0.04985566419],"iteration":392,"passed_time":2.788517747,"remaining_time":2.178307756},
{"learn":[0.04976345497],"iteration":393,"passed_time":2.797251951,"remaining_time":2.172485018},
{"learn":[0.04966870162],"iteration":394,"passed_time":2.804224142,"remaining_time":2.165286996},
{"learn":[0.04954000895],"iteration":395,"passed_time":2.810270802,"remaining_time":2.157379605},
{"learn":[0.04942099879],"iteration":396,"passed_time":2.816192771,"remaining_time":2.149386423},
{"learn":[0.04924174157],"iteration":397,"passed_time":2.822858373,"remaining_time":2.141967911},
{"learn":[0.04917521438],"iteration":398,"passed_time":2.828547584,"remaining_time":2.133816599},
{"learn":[0.04906991863],"iteration":399,"passed_time":2.834853128,"remaining_time":2.126139846},
{"learn":[0.04894005342],"iteration":400,"passed_time":2.841150176,"remaining_time":2.118463597},
{"learn":[0.04883751336],"iteration":401,"passed_time":2.848334911,"remaining_time":2.111452247},
{"learn":[0.04875987587],"iteration":402,"passed_time":2.855513712,"remaining_time":2.104435664},
{"learn":[0.04871949535],"iteration":403,"passed_time":2.861045199,"remaining_time":2.096211334},
{"learn":[0.04863880831],"iteration":404,"passed_time":2.866544139,"remaining_time":2.087976595},
{"learn":[0.04849518333],"iteration":405,"passed_time":2.872140477,"remaining_time":2.079825863},
{"learn":[0.04839049262],"iteration":406,"passed_time":2.87838112,"remaining_time":2.072151519},
{"learn":[0.04826970534],"iteration":407,"passed_time":2.885403682,"remaining_time":2.065043812},
{"learn":[0.04820723363],"iteration":408,"passed_time":2.891288252,"remaining_time":2.057126849},
{"learn":[0.04817792871],"iteration":409,"passed_time":2.896367578,"remaining_time":2.048650238},
{"learn":[0.04805333565],"iteration":410,"passed_time":2.904562464,"remaining_time":2.042380905},
{"learn":[0.0479471025],"iteration":411,"passed_time":2.912167337,"remaining_time":2.035689789},
{"learn":[0.04784656424],"iteration":412,"passed_time":2.920354765,"remaining_time":2.029399074},
{"learn":[0.04773729975],"iteration":413,"passed_time":2.927371793,"remaining_time":2.022290659},
{"learn":[0.04762686055],"iteration":414,"passed_time":2.934995445,"remaining_time":2.015599281},
{"learn":[0.04751394107],"iteration":415,"passed_time":2.942252057,"remaining_time":2.008652846},
{"learn":[0.04741959388],"iteration":416,"passed_time":2.950595949,"remaining_time":2.002442814},
{"learn":[0.04731670657],"iteration":417,"passed_time":2.958955274,"remaining_time":1.996232984},
{"learn":[0.04727112131],"iteration":418,"passed_time":2.964467784,"remaining_time":1.988103693},
{"learn":[0.04720971695],"iteration":419,"passed_time":2.971248124,"remaining_time":1.980832083},
{"learn":[0.04710715464],"iteration":420,"passed_time":2.977656479,"remaining_time":1.973316289},
{"learn":[0.0470488846],"iteration":421,"passed_time":2.984329884,"remaining_time":1.96598035},
{"learn":[0.04690587518],"iteration":422,"passed_time":2.991546305,"remaining_time":1.959003136},
{"learn":[0.04685425108],"iteration":423,"passed_time":2.998784166,"remaining_time":1.952038749},
{"learn":[0.04671228967],"iteration":424,"passed_time":3.004938966,"remaining_time":1.944372272},
{"learn":[0.04662635347],"iteration":425,"passed_time":3.011266134,"remaining_time":1.936823758},
{"learn":[0.04650734342],"iteration":426,"passed_time":3.016849159,"remaining_time":1.9288052},
{"learn":[0.04641795897],"iteration":427,"passed_time":3.022961,"remaining_time":1.921134094},
{"learn":[0.0463073032],"iteration":428,"passed_time":3.029996589,"remaining_time":1.914053789},
{"learn":[0.04620867596],"iteration":429,"passed_time":3.037391794,"remaining_time":1.907199499},
{"learn":[0.04611246664],"iteration":430,"passed_time":3.043297867,"remaining_time":1.899413286},
{"learn":[0.04601378786],"iteration":431,"passed_time":3.050788612,"remaining_time":1.892618861},
{"learn":[0.04593704271],"iteration":432,"passed_time":3.058375547,"remaining_time":1.885880533},
{"learn":[0.04586257213],"iteration":433,"passed_time":3.065095127,"remaining_time":1.878606691},
{"learn":[0.04579785946],"iteration":434,"passed_time":3.070113571,"remaining_time":1.870299072},
{"learn":[0.04571507315],"iteration":435,"passed_time":3.075807463,"remaining_time":1.862415528},
{"learn":[0.04557618844],"iteration":436,"passed_time":3.082094237,"remaining_time":1.85489882},
{"learn":[0.04546277965],"iteration":437,"passed_time":3.089185462,"remaining_time":1.847868929},
{"learn":[0.04533492175],"iteration":438,"passed_time":3.096773033,"remaining_time":1.841133853},
{"learn":[0.04520867478],"iteration":439,"passed_time":3.103274939,"remaining_time":1.833753373},
{"learn":[0.04513756622],"iteration":440,"passed_time":3.109324757,"remaining_time":1.826111365},
{"learn":[0.04503522442],"iteration":441,"passed_time":3.115436101,"remaining_time":1.818512475},
{"learn":[0.04490336673],"iteration":442,"passed_time":3.121792187,"remaining_time":1.811062284},
{"learn":[0.04486638392],"iteration":443,"passed_time":3.127819295,"remaining_time":1.803427341},
{"learn":[0.04478186785],"iteration":444,"passed_time":3.134240207,"remaining_time":1.796025287},
{"learn":[0.04468379701],"iteration":445,"passed_time":3.140563757,"remaining_time":1.788572184},
{"learn":[0.04457702572],"iteration":446,"passed_time":3.146371828,"remaining_time":1.780832377},
{"learn":[0.04455169067],"iteration":447,"passed_time":3.15260966,"remaining_time":1.773342933},
{"learn":[0.04445532406],"iteration":448,"passed_time":3.15823897,"remaining_time":1.76551889},
{"learn":[0.04442510937],"iteration":449,"passed_time":3.164397926,"remaining_time":1.757998848},
{"learn":[0.04441212331],"iteration":450,"passed_time":3.169982959,"remaining_time":1.750167975},
{"learn":[0.04435152145],"iteration":451,"passed_time":3.175414703,"remaining_time":1.742262934},
{"learn":[0.04426841282],"iteration":452,"passed_time":3.18151776,"remaining_time":1.73473485},
{"learn":[0.04418894329],"iteration":453,"passed_time":3.187348081,"remaining_time":1.72706526},
{"learn":[0.04404241476],"iteration":454,"passed_time":3.194527683,"remaining_time":1.720130291},
{"learn":[0.04398323401],"iteration":455,"passed_time":3.200739569,"remaining_time":1.712676436},
{"learn":[0.04390640863],"iteration":456,"passed_time":3.20697599,"remaining_time":1.705241062},
{"learn":[0.04388994962],"iteration":457,"passed_time":3.213095317,"remaining_time":1.697749054},
{"learn":[0.04378096864],"iteration":458,"passed_time":3.220018895,"remaining_time":1.690685302},
{"learn":[0.04374885874],"iteration":459,"passed_time":3.227577213,"remaining_time":1.683953329},
{"learn":[0.04365942666],"iteration":460,"passed_time":3.233398875,"remaining_time":1.676317421},
{"learn":[0.04358817516],"iteration":461,"passed_time":3.24007486,"remaining_time":1.669129473},
{"learn":[0.04347744274],"iteration":462,"passed_time":3.246008618,"remaining_time":1.661563807},
{"learn":[0.04336707769],"iteration":463,"passed_time":3.25247233,"remaining_time":1.654274719},
{"learn":[0.04332611537],"iteration":464,"passed_time":3.257706401,"remaining_time":1.646367751},
{"learn":[0.04329021646],"iteration":465,"passed_time":3.26280971,"remaining_time":1.638406593},
{"learn":[0.04327274999],"iteration":466,"passed_time":3.268620468,"remaining_time":1.63081064},
{"learn":[0.04323375522],"iteration":467,"passed_time":3.274133462,"remaining_time":1.623074708},
{"learn":[0.04311554015],"iteration":468,"passed_time":3.28054168,"remaining_time":1.615789186},
{"learn":[0.04304967734],"iteration":469,"passed_time":3.286029661,"remaining_time":1.608057068},
{"learn":[0.04296478136],"iteration":470,"passed_time":3.29211041,"remaining_time":1.600622683},
{"learn":[0.04289098826],"iteration":471,"passed_time":3.298693488,"remaining_time":1.593436685},
{"learn":[0.04282591486],"iteration":472,"passed_time":3.304908815,"remaining_time":1.586076746},
{"learn":[0.0427533359],"iteration":473,"passed_time":3.310207862,"remaining_time":1.578284761},
{"learn":[0.04270322204],"iteration":474,"passed_time":3.315351004,"remaining_time":1.570429423},
{"learn":[0.04263814234],"iteration":475,"passed_time":3.321190296,"remaining_time":1.56291308},
{"learn":[0.04254387463],"iteration":476,"passed_time":3.327040218,"remaining_time":1.555408739},
{"learn":[0.04245257206],"iteration":477,"passed_time":3.332036252,"remaining_time":1.547514745},
{"learn":[0.04234154202],"iteration":478,"passed_time":3.337690817,"remaining_time":1.539936682},
{"learn":[0.04223430582],"iteration":479,"passed_time":3.343324186,"remaining_time":1.532356919},
{"learn":[0.0421367787],"iteration":480,"passed_time":3.349453842,"remaining_time":1.525011209},
{"learn":[0.04211147012],"iteration":481,"passed_time":3.354640946,"remaining_time":1.517244245},
{"learn":[0.04201576173],"iteration":482,"passed_time":3.360095334,"remaining_time":1.509608049},
{"learn":[0.04195863957],"iteration":483,"passed_time":3.368013525,"remaining_time":1.503080416},
{"learn":[0.04190009861],"iteration":484,"passed_time":3.374739263,"remaining_time":1.496018436},
{"learn":[0.04183527098],"iteration":485,"passed_time":3.380983993,"remaining_time":1.488746038},
{"learn":[0.04176134079],"iteration":486,"passed_time":3.38876372,"remaining_time":1.482149225},
{"learn":[0.04171264328],"iteration":487,"passed_time":3.398590986,"remaining_time":1.476437068},
{"learn":[0.04170179816],"iteration":488,"passed_time":3.405854223,"remaining_time":1.46960172},
{"learn":[0.04162219655],"iteration":489,"passed_time":3.412652802,"remaining_time":1.462565487},
{"learn":[0.04156865339],"iteration":490,"passed_time":3.419541299,"remaining_time":1.455568496},
{"learn":[0.04144036759],"iteration":491,"passed_time":3.425738965,"remaining_time":1.448279887},
{"learn":[0.04136990532],"iteration":492,"passed_time":3.431560868,"remaining_time":1.44083793},
{"learn":[0.04133587797],"iteration":493,"passed_time":3.440013948,"remaining_time":1.434499743},
{"learn":[0.04126356944],"iteration":494,"passed_time":3.446005661,"remaining_time":1.427133658},
{"learn":[0.04118053771],"iteration":495,"passed_time":3.45193762,"remaining_time":1.419748537},
{"learn":[0.04116534457],"iteration":496,"passed_time":3.458828482,"remaining_time":1.412760929},
{"learn":[0.04110023775],"iteration":497,"passed_time":3.464879035,"remaining_time":1.405432861},
{"learn":[0.04104765699],"iteration":498,"passed_time":3.470739499,"remaining_time":1.398033345},
{"learn":[0.04098140991],"iteration":499,"passed_time":3.478445887,"remaining_time":1.391378355},
{"learn":[0.04092392755],"iteration":500,"passed_time":3.486170594,"remaining_time":1.384726444},
{"learn":[0.04086100584],"iteration":501,"passed_time":3.492510177,"remaining_time":1.377523934},
{"learn":[0.04077362264],"iteration":502,"passed_time":3.498542913,"remaining_time":1.37020468},
{"learn":[0.04069683978],"iteration":503,"passed_time":3.506459119,"remaining_time":1.363622991},
{"learn":[0.04063061076],"iteration":504,"passed_time":3.513023912,"remaining_time":1.356514184},
{"learn":[0.0406136245],"iteration":505,"passed_time":3.518634922,"remaining_time":1.349041848},
{"learn":[0.04054514101],"iteration":506,"passed_time":3.524301967,"remaining_time":1.341598185},
{"learn":[0.04048070247],"iteration":507,"passed_time":3.531555265,"remaining_time":1.334761045},
{"learn":[0.04046332198],"iteration":508,"passed_time":3.537269969,"remaining_time":1.32734492},
{"learn":[0.04037273638],"iteration":509,"passed_time":3.543061222,"remaining_time":1.319963985},
{"learn":[0.0403170052],"iteration":510,"passed_time":3.550026336,"remaining_time":1.313023439},
{"learn":[0.04022091735],"iteration":511,"passed_time":3.557595363,"remaining_time":1.306304547},
{"learn":[0.04014325018],"iteration":512,"passed_time":3.566116488,"remaining_time":1.299929402},
{"learn":[0.04009396082],"iteration":513,"passed_time":3.573060666,"remaining_time":1.29297526},
{"learn":[0.04004171929],"iteration":514,"passed_time":3.579640485,"remaining_time":1.285890271},
{"learn":[0.04002863886],"iteration":515,"passed_time":3.586276028,"remaining_time":1.278827111},
{"learn":[0.03998615559],"iteration":516,"passed_time":3.591813899,"remaining_time":1.271377067},
{"learn":[0.03990129333],"iteration":517,"passed_time":3.59691825,"remaining_time":1.263782088},
{"learn":[0.03984813869],"iteration":518,"passed_time":3.602641025,"remaining_time":1.256412381},
{"learn":[0.03974600408],"iteration":519,"passed_time":3.608480315,"remaining_time":1.24908934},
{"learn":[0.03964611648],"iteration":520,"passed_time":3.614293057,"remaining_time":1.241762874},
{"learn":[0.03959791544],"iteration":521,"passed_time":3.621347529,"remaining_time":1.234865633},
{"learn":[0.03952978563],"iteration":522,"passed_time":3.629011523,"remaining_time":1.228174072},
{"learn":[0.03941762469],"iteration":523,"passed_time":3.634466491,"remaining_time":1.220736837},
{"learn":[0.03932966011],"iteration":524,"passed_time":3.640082073,"remaining_time":1.213360691},
{"learn":[0.03928866686],"iteration":525,"passed_time":3.645294241,"remaining_time":1.205857791},
{"learn":[0.03924114336],"iteration":526,"passed_time":3.65053408,"remaining_time":1.198372668},
{"learn":[0.03917959779],"iteration":527,"passed_time":3.655787548,"remaining_time":1.190900489},
{"learn":[0.03913431816],"iteration":528,"passed_time":3.660876707,"remaining_time":1.183383586},
{"learn":[0.03909218867],"iteration":529,"passed_time":3.666365961,"remaining_time":1.176004176},
{"learn":[0.03904203232],"iteration":530,"passed_time":3.672014474,"remaining_time":1.168682573},
{"learn":[0.03897370135],"iteration":531,"passed_time":3.677774981,"remaining_time":1.161402626},
{"learn":[0.03887623193],"iteration":532,"passed_time":3.683505442,"remaining_time":1.154118966},
{"learn":[0.03881981675],"iteration":533,"passed_time":3.689140135,"remaining_time":1.146811353},
{"learn":[0.03878254865],"iteration":534,"passed_time":3.694598351,"remaining_time":1.139455566},
{"learn":[0.03869768747],"iteration":535,"passed_time":3.6996701,"remaining_time":1.131988613},
{"learn":[0.03863655077],"iteration":536,"passed_time":3.705638093,"remaining_time":1.124802624},
{"learn":[0.03862970925],"iteration":537,"passed_time":3.710938085,"remaining_time":1.117420018},
{"learn":[0.03857180568],"iteration":538,"passed_time":3.716262577,"remaining_time":1.110052458},
{"learn":[0.03850022658],"iteration":539,"passed_time":3.722261306,"remaining_time":1.102892239},
{"learn":[0.03843151978],"iteration":540,"passed_time":3.727950439,"remaining_time":1.095645323},
{"learn":[0.03840216027],"iteration":541,"passed_time":3.733223989,"remaining_time":1.088283008},
{"learn":[0.03833744307],"iteration":542,"passed_time":3.738781804,"remaining_time":1.081010577},
{"learn":[0.03825275194],"iteration":543,"passed_time":3.743714962,"remaining_time":1.07356532},
{"learn":[0.0381900961],"iteration":544,"passed_time":3.748849931,"remaining_time":1.066186678},
{"learn":[0.03810383154],"iteration":545,"passed_time":3.754492851,"remaining_time":1.058959522},
{"learn":[0.03802204777],"iteration":546,"passed_time":3.759944561,"remaining_time":1.051684676},
{"learn":[0.0379499556],"iteration":547,"passed_time":3.765195183,"remaining_time":1.044360708},
{"learn":[0.03789431294],"iteration":548,"passed_time":3.770669013,"remaining_time":1.037105685},
{"learn":[0.03780824109],"iteration":549,"passed_time":3.776216076,"remaining_time":1.029877112},
{"learn":[0.03775276076],"iteration":550,"passed_time":3.782406925,"remaining_time":1.022828733},
{"learn":[0.03767016621],"iteration":551,"passed_time":3.789184156,"remaining_time":1.01594068},
{"learn":[0.03765567001],"iteration":552,"passed_time":3.794025883,"remaining_time":1.008538526},
{"learn":[0.03761678621],"iteration":553,"passed_time":3.799599562,"remaining_time":1.001338513},
{"learn":[0.03760925773],"iteration":554,"passed_time":3.804918274,"remaining_time":0.9940777472},
{"learn":[0.03753592929],"iteration":555,"passed_time":3.810094884,"remaining_time":0.9867871643},
{"learn":[0.03746575044],"iteration":556,"passed_time":3.815552146,"remaining_time":0.9795762243},
{"learn":[0.03741575626],"iteration":557,"passed_time":3.821295637,"remaining_time":0.9724444094},
{"learn":[0.03731578757],"iteration":558,"passed_time":3.827038879,"remaining_time":0.9653174989},
{"learn":[0.03724689199],"iteration":559,"passed_time":3.83235079,"remaining_time":0.9580876975},
{"learn":[0.0372361751],"iteration":560,"passed_time":3.837867393,"remaining_time":0.9509154502},
{"learn":[0.03719286773],"iteration":561,"passed_time":3.842959868,"remaining_time":0.9436449499},
{"learn":[0.03714296312],"iteration":562,"passed_time":3.849896139,"remaining_time":0.9368308545},
{"learn":[0.03706303399],"iteration":563,"passed_time":3.854862039,"remaining_time":0.9295412009},
{"learn":[0.03697621503],"iteration":564,"passed_time":3.85989081,"remaining_time":0.9222747953},
{"learn":[0.0368926639],"iteration":565,"passed_time":3.865387545,"remaining_time":0.9151270865},
{"learn":[0.03683753053],"iteration":566,"passed_time":3.870926267,"remaining_time":0.9079950503},
{"learn":[0.03675703334],"iteration":567,"passed_time":3.876488376,"remaining_time":0.9008740593},
{"learn":[0.03669247251],"iteration":568,"passed_time":3.882439215,"remaining_time":0.8938480441},
{"learn":[0.03658795133],"iteration":569,"passed_time":3.888366529,"remaining_time":0.8868204364},
{"learn":[0.0365396918],"iteration":570,"passed_time":3.893241408,"remaining_time":0.8795589171},
{"learn":[0.03645556212],"iteration":571,"passed_time":3.897760248,"remaining_time":0.8722260695},
{"learn":[0.0364303719],"iteration":572,"passed_time":3.902171868,"remaining_time":0.8648792797},
{"learn":[0.03636564073],"iteration":573,"passed_time":3.906717603,"remaining_time":0.8575721567},
{"learn":[0.03631170155],"iteration":574,"passed_time":3.911306165,"remaining_time":0.850283949},
{"learn":[0.03625533851],"iteration":575,"passed_time":3.916490071,"remaining_time":0.8431332792},
{"learn":[0.0362456012],"iteration":576,"passed_time":3.921852553,"remaining_time":0.8360274939},
{"learn":[0.03615481047],"iteration":577,"passed_time":3.9277065,"remaining_time":0.8290314758},
{"learn":[0.03611908618],"iteration":578,"passed_time":3.935715474,"remaining_time":0.8224897622},
{"learn":[0.03605683594],"iteration":579,"passed_time":3.943895807,"remaining_time":0.8159784429},
{"learn":[0.03598479815],"iteration":580,"passed_time":3.950243527,"remaining_time":0.8090860236},
{"learn":[0.03593363225],"iteration":581,"passed_time":3.955746629,"remaining_time":0.8020242306},
{"learn":[0.03587471801],"iteration":582,"passed_time":3.961549449,"remaining_time":0.795027934},
{"learn":[0.03580948064],"iteration":583,"passed_time":3.966810727,"remaining_time":0.787928158},
{"learn":[0.03575776297],"iteration":584,"passed_time":3.972115145,"remaining_time":0.7808431481},
{"learn":[0.03570323794],"iteration":585,"passed_time":3.979017791,"remaining_time":0.7740751334},
{"learn":[0.03560514027],"iteration":586,"passed_time":3.984340352,"remaining_time":0.7670024868},
{"learn":[0.03559679201],"iteration":587,"passed_time":3.989413715,"remaining_time":0.7598883267},
{"learn":[0.03554981409],"iteration":588,"passed_time":3.996169681,"remaining_time":0.7530981911},
{"learn":[0.03549500689],"iteration":589,"passed_time":4.002398309,"remaining_time":0.7462098542},
{"learn":[0.03546304507],"iteration":590,"passed_time":4.008621489,"remaining_time":0.739322745},
{"learn":[0.03540818253],"iteration":591,"passed_time":4.017088806,"remaining_time":0.7328472823},
{"learn":[0.0353446807],"iteration":592,"passed_time":4.024191778,"remaining_time":0.7261189212},
{"learn":[0.03526233149],"iteration":593,"passed_time":4.030590529,"remaining_time":0.7192636297},
{"learn":[0.03520457514],"iteration":594,"passed_time":4.03559798,"remaining_time":0.7121643493},
{"learn":[0.03514763162],"iteration":595,"passed_time":4.04304509,"remaining_time":0.7054978009},
{"learn":[0.03509286898],"iteration":596,"passed_time":4.049322849,"remaining_time":0.6986268901},
{"learn":[0.03502745328],"iteration":597,"passed_time":4.055512215,"remaining_time":0.6917428861},
{"learn":[0.03502053991],"iteration":598,"passed_time":4.062176972,"remaining_time":0.6849413592},
{"learn":[0.0349868869],"iteration":599,"passed_time":4.068293598,"remaining_time":0.6780489329},
{"learn":[0.0349206058],"iteration":600,"passed_time":4.074905745,"remaining_time":0.6712407135},
{"learn":[0.03487249701],"iteration":601,"passed_time":4.081123063,"remaining_time":0.6643688707},
{"learn":[0.0348000378],"iteration":602,"passed_time":4.08660933,"remaining_time":0.6573816003},
{"learn":[0.0347328087],"iteration":603,"passed_time":4.092605969,"remaining_time":0.6504804189},
{"learn":[0.03464936329],"iteration":604,"passed_time":4.097916722,"remaining_time":0.6434745266},
{"learn":[0.03457136929],"iteration":605,"passed_time":4.104634206,"remaining_time":0.6366924345},
{"learn":[0.03449592661],"iteration":606,"passed_time":4.11017458,"remaining_time":0.6297302075},
{"learn":[0.03440071689],"iteration":607,"passed_time":4.115453183,"remaining_time":0.6227330475},
{"learn":[0.0343343237],"iteration":608,"passed_time":4.121961578,"remaining_time":0.6159252932},
{"learn":[0.03426155966],"iteration":609,"passed_time":4.127200594,"remaining_time":0.6089312352},
{"learn":[0.03420697157],"iteration":610,"passed_time":4.132189509,"remaining_time":0.6019064915},
{"learn":[0.03417687071],"iteration":611,"passed_time":4.138551644,"remaining_time":0.5950858573},
{"learn":[0.03411771148],"iteration":612,"passed_time":4.144289462,"remaining_time":0.5881781128},
{"learn":[0.03404141835],"iteration":613,"passed_time":4.149628466,"remaining_time":0.5812183193},
{"learn":[0.03403467244],"iteration":614,"passed_time":4.155575874,"remaining_time":0.574347885},
{"learn":[0.03393775446],"iteration":615,"passed_time":4.160957642,"remaining_time":0.5674033149},
{"learn":[0.03388642594],"iteration":616,"passed_time":4.168153171,"remaining_time":0.5607078009},
{"learn":[0.0338225524],"iteration":617,"passed_time":4.174189432,"remaining_time":0.5538568502},
{"learn":[0.03373815342],"iteration":618,"passed_time":4.180136738,"remaining_time":0.5469968914},
{"learn":[0.03367868514],"iteration":619,"passed_time":4.188481663,"remaining_time":0.5404492468},
{"learn":[0.03361890433],"iteration":620,"passed_time":4.194194644,"remaining_time":0.5335609934},
{"learn":[0.03361265893],"iteration":621,"passed_time":4.19975331,"remaining_time":0.5266571675},
{"learn":[0.03356503918],"iteration":622,"passed_time":4.206021409,"remaining_time":0.5198453427},
{"learn":[0.03352896703],"iteration":623,"passed_time":4.212023892,"remaining_time":0.51300291},
{"learn":[0.03348976785],"iteration":624,"passed_time":4.218495075,"remaining_time":0.506219409},
{"learn":[0.03345724689],"iteration":625,"passed_time":4.224785788,"remaining_time":0.4994155724},
{"learn":[0.03340191624],"iteration":626,"passed_time":4.230195262,"remaining_time":0.4925107721},
{"learn":[0.03335474025],"iteration":627,"passed_time":4.237471727,"remaining_time":0.485824784},
{"learn":[0.03328898593],"iteration":628,"passed_time":4.242885748,"remaining_time":0.4789266902},
{"learn":[0.03327759468],"iteration":629,"passed_time":4.249885721,"remaining_time":0.4722095246},
{"learn":[0.03320384815],"iteration":630,"passed_time":4.255935695,"remaining_time":0.4653875799},
{"learn":[0.03314333294],"iteration":631,"passed_time":4.261487624,"remaining_time":0.4585144912},
{"learn":[0.03311426696],"iteration":632,"passed_time":4.267793836,"remaining_time":0.4517254139},
{"learn":[0.03304634813],"iteration":633,"passed_time":4.273697038,"remaining_time":0.4448959061},
{"learn":[0.03299915975],"iteration":634,"passed_time":4.278628922,"remaining_time":0.4379698896},
{"learn":[0.03290993737],"iteration":635,"passed_time":4.285059656,"remaining_time":0.4312009717},
{"learn":[0.03283565534],"iteration":636,"passed_time":4.290532374,"remaining_time":0.4243383667},
{"learn":[0.03279693106],"iteration":637,"passed_time":4.295741059,"remaining_time":0.4174544603},
{"learn":[0.03271790857],"iteration":638,"passed_time":4.303711457,"remaining_time":0.4108394348},
{"learn":[0.03266109973],"iteration":639,"passed_time":4.309500266,"remaining_time":0.40401565},
{"learn":[0.03259821446],"iteration":640,"passed_time":4.315497538,"remaining_time":0.397214282},
{"learn":[0.03253136316],"iteration":641,"passed_time":4.321233553,"remaining_time":0.3903918163},
{"learn":[0.03247593955],"iteration":642,"passed_time":4.325947475,"remaining_time":0.3834821246},
{"learn":[0.03241270575],"iteration":643,"passed_time":4.331877499,"remaining_time":0.3766849999},
{"learn":[0.03236273891],"iteration":644,"passed_time":4.337474349,"remaining_time":0.3698621538},
{"learn":[0.03229775786],"iteration":645,"passed_time":4.342518088,"remaining_time":0.362996868},
{"learn":[0.03223578125],"iteration":646,"passed_time":4.348469101,"remaining_time":0.3562115338},
{"learn":[0.03217184123],"iteration":647,"passed_time":4.354360996,"remaining_time":0.3494240306},
{"learn":[0.03211169742],"iteration":648,"passed_time":4.361740878,"remaining_time":0.3427562169},
{"learn":[0.03207420521],"iteration":649,"passed_time":4.367389964,"remaining_time":0.3359530741},
{"learn":[0.03201141859],"iteration":650,"passed_time":4.372581575,"remaining_time":0.3291190433},
{"learn":[0.03194306632],"iteration":651,"passed_time":4.379936979,"remaining_time":0.3224493482},
{"learn":[0.0318820743],"iteration":652,"passed_time":4.384379648,"remaining_time":0.3155679073},
{"learn":[0.03185246169],"iteration":653,"passed_time":4.388712526,"remaining_time":0.3086862021},
{"learn":[0.03181495938],"iteration":654,"passed_time":4.397134916,"remaining_time":0.3020932385},
{"learn":[0.031760577],"iteration":655,"passed_time":4.402290729,"remaining_time":0.2952755977},
{"learn":[0.03166819817],"iteration":656,"passed_time":4.406818904,"remaining_time":0.2884219374},
{"learn":[0.03162765616],"iteration":657,"passed_time":4.41201875,"remaining_time":0.2816182181},
{"learn":[0.03157718049],"iteration":658,"passed_time":4.416596939,"remaining_time":0.2747806897},
{"learn":[0.03152960229],"iteration":659,"passed_time":4.420761243,"remaining_time":0.2679249238},
{"learn":[0.03150337153],"iteration":660,"passed_time":4.425879197,"remaining_time":0.2611335684},
{"learn":[0.03146141055],"iteration":661,"passed_time":4.430723739,"remaining_time":0.2543315741},
{"learn":[0.03141445821],"iteration":662,"passed_time":4.435352047,"remaining_time":0.2475234174},
{"learn":[0.03135769263],"iteration":663,"passed_time":4.439693054,"remaining_time":0.2407062499},
{"learn":[0.03134783968],"iteration":664,"passed_time":4.444986025,"remaining_time":0.2339466329},
{"learn":[0.03132118775],"iteration":665,"passed_time":4.450065221,"remaining_time":0.2271805068},
{"learn":[0.03123503142],"iteration":666,"passed_time":4.456058102,"remaining_time":0.2204646437},
{"learn":[0.03117602617],"iteration":667,"passed_time":4.461333502,"remaining_time":0.2137165749},
{"learn":[0.03113692929],"iteration":668,"passed_time":4.466168505,"remaining_time":0.2069525017},
{"learn":[0.03108963664],"iteration":669,"passed_time":4.471483697,"remaining_time":0.2002156879},
{"learn":[0.03103682317],"iteration":670,"passed_time":4.478320582,"remaining_time":0.1935488776},
{"learn":[0.0309976997],"iteration":671,"passed_time":4.48487138,"remaining_time":0.1868696408},
{"learn":[0.03093670831],"iteration":672,"passed_time":4.490472256,"remaining_time":0.1801526759},
{"learn":[0.03085425139],"iteration":673,"passed_time":4.495702716,"remaining_time":0.1734247339},
{"learn":[0.03082413774],"iteration":674,"passed_time":4.500980144,"remaining_time":0.1667029683},
{"learn":[0.03081883643],"iteration":675,"passed_time":4.506604053,"remaining_time":0.159997777},
{"learn":[0.03075083152],"iteration":676,"passed_time":4.512210704,"remaining_time":0.1532951938},
{"learn":[0.03068755032],"iteration":677,"passed_time":4.517105647,"remaining_time":0.1465727496},
{"learn":[0.03063974656],"iteration":678,"passed_time":4.522751063,"remaining_time":0.1398788989},
{"learn":[0.03057263737],"iteration":679,"passed_time":4.528554501,"remaining_time":0.1331927794},
{"learn":[0.03051821746],"iteration":680,"passed_time":4.53340634,"remaining_time":0.1264827026},
{"learn":[0.03045769725],"iteration":681,"passed_time":4.538913106,"remaining_time":0.1197953606},
{"learn":[0.03038489768],"iteration":682,"passed_time":4.543755564,"remaining_time":0.1130949408},
{"learn":[0.03034156628],"iteration":683,"passed_time":4.548260614,"remaining_time":0.1063920612},
{"learn":[0.0302836082],"iteration":684,"passed_time":4.55407958,"remaining_time":0.09972437037},
{"learn":[0.03025988974],"iteration":685,"passed_time":4.559072198,"remaining_time":0.09304228976},
{"learn":[0.03018694478],"iteration":686,"passed_time":4.564200611,"remaining_time":0.08636769716},
{"learn":[0.03012538545],"iteration":687,"passed_time":4.569331432,"remaining_time":0.07969764126},
{"learn":[0.03004260263],"iteration":688,"passed_time":4.574626486,"remaining_time":0.07303467539},
{"learn":[0.02999719563],"iteration":689,"passed_time":4.57987797,"remaining_time":0.06637504304},
{"learn":[0.02994222344],"iteration":690,"passed_time":4.585346469,"remaining_time":0.0597223129},
{"learn":[0.02987934083],"iteration":691,"passed_time":4.591386877,"remaining_time":0.05307961707},
{"learn":[0.02983019682],"iteration":692,"passed_time":4.596376038,"remaining_time":0.04642804079},
{"learn":[0.02980072967],"iteration":693,"passed_time":4.602223735,"remaining_time":0.03978867782},
{"learn":[0.02977414171],"iteration":694,"passed_time":4.608757992,"remaining_time":0.03315653232},
{"learn":[0.02971435786],"iteration":695,"passed_time":4.614428769,"remaining_time":0.02651970557},
{"learn":[0.02964430882],"iteration":696,"passed_time":4.620513831,"remaining_time":0.01988743399},
{"learn":[0.02957161807],"iteration":697,"passed_time":4.625542387,"remaining_time":0.01325370311},
{"learn":[0.02949677116],"iteration":698,"passed_time":4.63087779,"remaining_time":0.006625003992},
{"learn":[0.02945629735],"iteration":699,"passed_time":4.636388847,"remaining_time":0}
]}